streamhub/__init__.py
streamhub/messages_processor.py
streamhub/metadata_message.py
streamhub/notifications.py
streamhub-0.2.17.dist-info/LICENSE
streamhub-0.2.17.dist-info/METADATA
streamhub-0.2.17.dist-info/WHEEL
streamhub-0.2.17.dist-info/top_level.txt
streamhub-0.2.17.dist-info/RECORD
